nbtk/__init__.py
nbtk/fmtUtil.py
nbtk/nb_model.py
nbtk/jwa/__init__.py
nbtk/jwa/statics.py
nbtk/jwa/algorithm/__init__.py
nbtk/jwa/algorithm/k_means.py
nbtk/jwa/configuration/__init__.py
nbtk/jwa/configuration/yaml_configuration.py
nbtk/jwa/connector/__init__.py
nbtk/jwa/connector/connector.py
nbtk/jwa/connector/data.py
nbtk/jwa/connector/database.py
nbtk/jwa/connector/factory.py
nbtk/jwa/connector/mysql.py
nbtk/jwa/connector/postgresql.py
nbtk/jwa/log/__init__.py
nbtk/jwa/log/log_handler.py
nbtk/jwa/tests/__init__.py
nbtk/jwa/tests/kmeans_test.py
nbtk/util/__init__.py
nbtk/util/fmt.py
nbtk-0.1.3.dist-info/LICENSE
nbtk-0.1.3.dist-info/METADATA
nbtk-0.1.3.dist-info/WHEEL
nbtk-0.1.3.dist-info/top_level.txt
nbtk-0.1.3.dist-info/RECORD
