Metadata-Version: 2.1
Name: nbtk
Version: 0.1.3
Summary: Nebula Toolkit, serving developers and contributors of the Nebula platform.
Home-page: https://git.zjvis.org/bigdata/aiworks-py/tree/dev/nbtk
Author: @Nebula Team
Author-email: wzl@zhejianglab.com
License: UNKNOWN
Platform: UNKNOWN
Classifier: Programming Language :: Python :: 3
Classifier: License :: OSI Approved :: MIT License
Classifier: Operating System :: OS Independent
Requires-Python: >=3.6
License-File: LICENSE
